plotly_extend_wrapper/__init__.py
plotly_extend_wrapper/common.py
plotly_extend_wrapper/updater.py
plotly_extend_wrapper/wrapper.py
plotly_extend_wrapper-1.2.0.dist-info/METADATA
plotly_extend_wrapper-1.2.0.dist-info/WHEEL
plotly_extend_wrapper-1.2.0.dist-info/licenses/LICENSE
plotly_extend_wrapper-1.2.0.dist-info/RECORD
