Metadata-Version: 2.4
Name: plotly-extend-wrapper
Version: 1.2.0
Author-email: Laplusdestiny <prayonshootingstars@gmail.com>
License-File: LICENSE
Requires-Python: >=3.9
Requires-Dist: kaleido==0.2.1
Requires-Dist: nbformat>=4.2.0
Requires-Dist: numpy>=1.24.0
Requires-Dist: pandas>=2.0.0
Requires-Dist: plotly>=5.12.0
Requires-Dist: pyarrow>=10.0.0
Requires-Dist: scipy>=1.8.0
